ascord/__init__.py
ascord/ascordfuncs.py
ascord-1.0.0.dist-info/METADATA
ascord-1.0.0.dist-info/WHEEL
ascord-1.0.0.dist-info/top_level.txt
ascord-1.0.0.dist-info/RECORD
